magma/__init__.py
magma/checkstatus.py
magma/inputgenerator.py
magma/metawfl.py
magma/metawflrun.py
magma/runupdate.py
magma_ff/__init__.py
magma_ff/checkstatus.py
magma_ff/commands/__init__.py
magma_ff/commands/create_meta_workflow_run.py
magma_ff/create_metawfr.py
magma_ff/import_metawfr.py
magma_ff/inputgenerator.py
magma_ff/metawfl.py
magma_ff/metawflrun.py
magma_ff/parser.py
magma_ff/reset_metawfr.py
magma_ff/run_metawfr.py
magma_ff/runupdate.py
magma_ff/status_metawfr.py
magma_ff/update_cost_metawfr.py
magma_ff/utils.py
magma_ff/wfrutils.py
magma_smaht/__init__.py
magma_smaht/checkstatus.py
magma_smaht/commands/__init__.py
magma_smaht/commands/create_meta_workflow_run.py
magma_smaht/commands/wrangler_utils.py
magma_smaht/create_metawfr.py
magma_smaht/import_metawfr.py
magma_smaht/inputgenerator.py
magma_smaht/metawfl.py
magma_smaht/metawflrun.py
magma_smaht/parser.py
magma_smaht/reset_metawfr.py
magma_smaht/run_metawfr.py
magma_smaht/runupdate.py
magma_smaht/status_metawfr.py
magma_smaht/update_cost_metawfr.py
magma_smaht/utils.py
magma_smaht/wfrutils.py
magma_smaht/wrangler_utils.py
magma_suite-3.6.0.dist-info/LICENSE.txt
magma_suite-3.6.0.dist-info/METADATA
magma_suite-3.6.0.dist-info/WHEEL
magma_suite-3.6.0.dist-info/entry_points.txt
magma_suite-3.6.0.dist-info/RECORD
