Metadata-Version: 2.1
Name: magma-suite
Version: 3.6.0
Summary: Collection of tools to manage meta-workflows automation.
Home-page: https://github.com/dbmi-bgm/magma
License: MIT
Author: Michele Berselli
Author-email: berselli.michele@gmail.com
Requires-Python: >=3.8.1,<3.13
Classifier: License :: OSI Approved :: MIT License
Classifier: Operating System :: POSIX :: Linux
Classifier: Programming Language :: Python
Classifier: Programming Language :: Python :: 3
Classifier: Programming Language :: Python :: 3.9
Classifier: Programming Language :: Python :: 3.10
Classifier: Programming Language :: Python :: 3.11
Classifier: Programming Language :: Python :: 3.12
Requires-Dist: click (>=7.1.2,<8.0.0)
Requires-Dist: dcicutils (>=8.13.3,<9.0.0)
Requires-Dist: packaging (>=23.0,<24.0)
Requires-Dist: tibanna-ff (>=3.5.0,<4.0.0)
Project-URL: Repository, https://github.com/dbmi-bgm/magma
